LICENSE
MANIFEST.in
README.md
requirements.txt
setup.py
sportsball/__init__.py
sportsball/__main__.py
sportsball/args.py
sportsball/cache.py
sportsball/logger.py
sportsball/loglevel.py
sportsball/playwright.py
sportsball/sportsball.py
sportsball.egg-info/PKG-INFO
sportsball.egg-info/SOURCES.txt
sportsball.egg-info/dependency_links.txt
sportsball.egg-info/entry_points.txt
sportsball.egg-info/not-zip-safe
sportsball.egg-info/requires.txt
sportsball.egg-info/top_level.txt
sportsball/data/__init__.py
sportsball/data/address_model.py
sportsball/data/bet.py
sportsball/data/bookie_model.py
sportsball/data/coach_model.py
sportsball/data/delimiter.py
sportsball/data/dividend_model.py
sportsball/data/field_type.py
sportsball/data/game_model.py
sportsball/data/league.py
sportsball/data/league_model.py
sportsball/data/model.py
sportsball/data/news_model.py
sportsball/data/odds_model.py
sportsball/data/owner_model.py
sportsball/data/player_model.py
sportsball/data/season_type.py
sportsball/data/sex.py
sportsball/data/social_model.py
sportsball/data/species.py
sportsball/data/team_model.py
sportsball/data/umpire_model.py
sportsball/data/venue_model.py
sportsball/data/weather_model.py
sportsball/data/afl/__init__.py
sportsball/data/afl/position.py
sportsball/data/afl/afl/__init__.py
sportsball/data/afl/afl/afl_afl_bookie_model.py
sportsball/data/afl/afl/afl_afl_game_model.py
sportsball/data/afl/afl/afl_afl_league_model.py
sportsball/data/afl/afl/afl_afl_odds_model.py
sportsball/data/afl/afl/afl_afl_player_model.py
sportsball/data/afl/afl/afl_afl_team_model.py
sportsball/data/afl/afl/afl_afl_umpire_model.py
sportsball/data/afl/afl/afl_afl_venue_model.py
sportsball/data/afl/afltables/__init__.py
sportsball/data/afl/afltables/afl_afltables_coach_model.py
sportsball/data/afl/afltables/afl_afltables_game_model.py
sportsball/data/afl/afltables/afl_afltables_league_model.py
sportsball/data/afl/afltables/afl_afltables_player_model.py
sportsball/data/afl/afltables/afl_afltables_team_model.py
sportsball/data/afl/afltables/afl_afltables_umpire_model.py
sportsball/data/afl/afltables/afl_afltables_venue_model.py
sportsball/data/afl/aussportsbetting/__init__.py
