Metadata-Version: 2.2
Name: sportsball
Version: 0.34.137
Summary: A library for pulling in and normalising sports stats.
Home-page: https://github.com/8W9aG/sportsball
Author: Will Sackfield
Author-email: will.sackfield@gmail.com
License: MIT
Keywords: sports data betting
Classifier: License :: OSI Approved :: MIT License
Classifier: Programming Language :: Python :: 3
License-File: LICENSE
Requires-Dist: pandas>=2.2.3
Requires-Dist: requests>=2.31.0
Requires-Dist: requests-cache>=1.2.0
Requires-Dist: python-dateutil>=1.16.0
Requires-Dist: tqdm>=4.66.2
Requires-Dist: beautifulsoup4>=4.13.4
Requires-Dist: openpyxl>=3.1.5
Requires-Dist: joblib>=1.4.2
Requires-Dist: pyarrow>=18.0.0
Requires-Dist: ipython>=8.29.0
Requires-Dist: python-dateutil>=1.16.0
Requires-Dist: pytz>=2024.1
Requires-Dist: python-dotenv>=1.0.1
Requires-Dist: geocoder>=1.38.1
Requires-Dist: retry-requests>=2.0.0
Requires-Dist: openmeteo-requests>=1.3.0
Requires-Dist: nba_api>=1.9.0
Requires-Dist: timezonefinder>=6.6.3
Requires-Dist: pydantic>=2.11.9
Requires-Dist: flatten_json>=0.1.14
Requires-Dist: extruct>=0.18.0
Requires-Dist: wikipedia-api>=0.8.1
Requires-Dist: tweepy>=4.15.0
Requires-Dist: pytest-is-running>=1.5.1
Requires-Dist: PySocks>=1.7.1
Requires-Dist: func-timeout>=4.3.5
Requires-Dist: tenacity>=9.0.0
Requires-Dist: random_user_agent>=1.0.1
Requires-Dist: wayback>=0.4.5
Requires-Dist: cryptography>=44.0.0
Requires-Dist: feedparser>=6.0.11
Requires-Dist: dateparser>=1.2.0
Requires-Dist: playwright>=1.51.0
Requires-Dist: cchardet>=2.2.0a2
Requires-Dist: lxml>=5.3.0
Requires-Dist: gender-guesser>=0.4.0
Requires-Dist: scrapesession>=0.0.17
Requires-Dist: pyhigh>=0.0.6
Requires-Dist: datefinder>=0.7.3
Dynamic: author
Dynamic: author-email
Dynamic: classifier
Dynamic: description
Dynamic: description-content-type
Dynamic: home-page
Dynamic: keywords
Dynamic: license
Dynamic: requires-dist
Dynamic: summary
